{
  "hms": [
    { "name": "Montura Wyrdeer", "location": "Tras derrotar al Noble Kleavor — movimiento rápido por tierra" },
    { "name": "Montura Ursaluna", "location": "Tras derrotar al Noble Lilligant — buscar tesoros enterrados" },
    { "name": "Montura Basculegion", "location": "Tras derrotar al Noble Arcanine — navegar por agua" },
    { "name": "Montura Sneasler", "location": "Tras derrotar al Noble Electrode — escalar acantilados" },
    { "name": "Montura Braviary Hisuian", "location": "Tras derrotar al Noble Avalugg — volar y planear" }
  ],
  "tms": [
    { "name": "Semilla Tutora: Terremoto", "location": "Vendedor en Villa Jubileo — nivel 5 de rango" },
    { "name": "Semilla Tutora: Rayo Hielo", "location": "Vendedor en Villa Jubileo — nivel 5 de rango" },
    { "name": "Semilla Tutora: Lanzallamas", "location": "Vendedor en Villa Jubileo — nivel 5 de rango" },
    { "name": "Semilla Tutora: Rayo", "location": "Vendedor en Villa Jubileo — nivel 5 de rango" },
    { "name": "Semilla Tutora: Bola Sombra", "location": "Vendedor en Villa Jubileo — nivel 6 de rango" },
    { "name": "Semilla Tutora: Energibola", "location": "Vendedor en Villa Jubileo — nivel 4 de rango" },
    { "name": "Semilla Tutora: Psíquico", "location": "Vendedor en Villa Jubileo — nivel 6 de rango" },
    { "name": "Semilla Tutora: Garra Dragón", "location": "Vendedor en Villa Jubileo — nivel 7 de rango" },
    { "name": "Semilla Tutora: Danza Espada", "location": "Vendedor en Villa Jubileo — nivel 5 de rango" },
    { "name": "Semilla Tutora: Paz Mental", "location": "Vendedor en Villa Jubileo — nivel 6 de rango" }
  ]
}
