{
  "members": [
    { "name": "Emboar", "moves": ["Llamarada", "Onda Certera", "Roca Afilada", "Terremoto"], "notes": "Tu inicial Fuego/Lucha. Atacante mixto potente.", "emoji": "🐗" },
    { "name": "Azumarill", "moves": ["Acua Cola", "Carantoña", "Surf", "Chorro de Agua"], "notes": "Azurill en la Ruta 20. Tipo Agua/Hada con Potencia Enorme.", "emoji": "💧" },
    { "name": "Roserade", "moves": ["Gigadrenaje", "Bomba Lodo", "Tóxico", "Día Soleado"], "notes": "Roselia en la Ruta 12. Buen especial con cobertura de Veneno.", "emoji": "🌹" },
    { "name": "Espeon", "moves": ["Psíquico", "Bola Sombra", "Señal", "Paz Mental"], "notes": "Eevee disponible en las alcantarillas de Castelia. Evoluciona con amistad de día.", "emoji": "🔮" },
    { "name": "Electivire", "moves": ["Rayo", "Puño Hielo", "Puño Fuego", "Demolición"], "notes": "Elekid en la Ruta de Virbank. Potente atacante físico eléctrico.", "emoji": "⚡" },
    { "name": "Flygon", "moves": ["Terremoto", "Garra Dragón", "Ida y Vuelta", "Roca Afilada"], "notes": "Trapinch en la Ruta 4. Cobertura Tierra/Dragón.", "emoji": "🐉" }
  ]
}
