{
  "id": "shield",
  "name": "Pokémon Shield",
  "generation": 8,
  "region": "Galar",
  "releaseYear": 2019,
  "platform": "Switch",
  "accentColor": "#E02D60",
  "secondaryColor": "#B01A45",
  "icon": "shield.fill",
  "starters": [
    { "dexNumber": 810, "name": "Grookey" },
    { "dexNumber": 813, "name": "Scorbunny" },
    { "dexNumber": 816, "name": "Sobble" }
  ],
  "gymCount": 8,
  "hasEliteFour": false,
  "hasChampion": true,
  "regionalDex": [
    { "regionalNumber": 1, "nationalDex": 810, "location": "Pueblo Postwick (inicial)" },
    { "regionalNumber": 2, "nationalDex": 811, "location": "Evolucionar Grookey" },
    { "regionalNumber": 3, "nationalDex": 812, "location": "Evolucionar Thwackey" },
    { "regionalNumber": 4, "nationalDex": 813, "location": "Pueblo Postwick (inicial)" },
    { "regionalNumber": 5, "nationalDex": 814, "location": "Evolucionar Scorbunny" },
    { "regionalNumber": 6, "nationalDex": 815, "location": "Evolucionar Raboot" },
    { "regionalNumber": 7, "nationalDex": 816, "location": "Pueblo Postwick (inicial)" },
    { "regionalNumber": 8, "nationalDex": 817, "location": "Evolucionar Sobble" },
    { "regionalNumber": 9, "nationalDex": 818, "location": "Evolucionar Drizzile" },
    { "regionalNumber": 10, "nationalDex": 824, "location": "Ruta 1" },
    { "regionalNumber": 11, "nationalDex": 825, "location": "Evolucionar Blipbug" },
    { "regionalNumber": 12, "nationalDex": 826, "location": "Evolucionar Dottler" },
    { "regionalNumber": 13, "nationalDex": 10, "location": "Ruta 1" },
    { "regionalNumber": 14, "nationalDex": 11, "location": "Evolucionar Caterpie" },
    { "regionalNumber": 15, "nationalDex": 12, "location": "Evolucionar Metapod" }
  ],
  "versionExclusives": {
    "shield": [222, 538, 453, 454, 629, 630, 765, 780, 246, 247, 248, 841, 875, 889],
    "sword": [83, 539, 554, 555, 627, 628, 766, 776, 782, 783, 784, 842, 874, 888]
  }
}
